unified_io/__init__.py
unified_io/utils.py
unified_io/handlers/__init__.py
unified_io/handlers/common.py
unified_io/handlers/csv_handler.py
unified_io/handlers/gzip_handler.py
unified_io/handlers/json_handler.py
unified_io/handlers/jsonl_handler.py
unified_io/handlers/list_handler.py
unified_io/handlers/lz4_handler.py
unified_io/handlers/numpy_handler.py
unified_io/handlers/path_handler.py
unified_io/handlers/pickle_handler.py
unified_io/handlers/string_handler.py
unified_io-0.1.1.dist-info/LICENSE
unified_io-0.1.1.dist-info/METADATA
unified_io-0.1.1.dist-info/WHEEL
unified_io-0.1.1.dist-info/top_level.txt
unified_io-0.1.1.dist-info/RECORD
