Metadata-Version: 2.1
Name: unified-io
Version: 0.1.1
Summary: Unified I/O interface for Python
Home-page: https://github.com/AmenRa/unified-io
Author: Elias Bassani
Author-email: elias.bssn@gmail.com
Keywords: io,oneliner,oneliners,utils,utilities
Classifier: Programming Language :: Python :: 3
Classifier: License :: OSI Approved :: MIT License
Classifier: Intended Audience :: Science/Research
Classifier: Operating System :: OS Independent
Classifier: Topic :: Text Processing :: General
Requires-Python: >=3.7
License-File: LICENSE
Requires-Dist: numpy
Requires-Dist: orjson
Requires-Dist: lz4
